<?xml version="1.0" encoding="UTF-8"?>
<!DOCTYPE PAPER
  SYSTEM "paper-structure-annotation.dtd">
<PAPER><mode2 name="b310282c" hasDoc="yes" version="1153"/><TITLE><s sid="1"><CoreSc1 atype="GSC" type="Obj" conceptID="Obj1" novelty="New" advantage="None"/><text>Microfluidic flow transducer based on the measurement of electrical admittance</text></s></TITLE><ABSTRACT><s sid="2"><CoreSc1 atype="GSC" type="Obj" conceptID="Obj1" novelty="New" advantage="None"/><text>A new flow transducer for measuring the flow rate of a conducting fluid in a microchannel is reported.</text></s> <s sid="3"><CoreSc1 atype="GSC" type="Met" conceptID="Met1" novelty="New" advantage="None"/><text>In this paper, the measure of flow of such fluid under laminar flow conditions based on the change of electrical admittance is established with the aid of a pair of electrodes parallel to the line of flow in a glass–PDMS microfluidic device.</text></s> <s sid="4"><CoreSc1 atype="GSC" type="Met" conceptID="Met1" novelty="New" advantage="Yes"/><text>This flow sensor is simple in design and can be integrated to most of the microfluidic platforms.</text></s> <s sid="5"><CoreSc1 atype="GSC" type="Goa" conceptID="Goa1" novelty="None" advantage="None"/><text>The effect of flow rate of the electrolyte, the frequency of the applied ac voltage, the voltage applied across the detector electrodes, and the conductivity of the electrolyte are varied to optimize for high sensitivity.</text></s> <s sid="6"><CoreSc1 atype="GSC" type="Goa" conceptID="Goa1" novelty="None" advantage="None"/><text>The optimized values are then used to demonstrate the measurements of very low flow rates (&lt;1 nL s<SP>–1</SP>).</text></s> <s sid="7"><CoreSc1 atype="GSC" type="Met" conceptID="Met1" novelty="New" advantage="Yes"/><text>This flow sensor can be extended towards the measurement of chemical and biochemical buffers and reagents.</text></s></ABSTRACT><BODY><DIV DEPTH="1"><HEADER>Introduction</HEADER><P><s sid="8"><CoreSc1 atype="GSC" type="Mot" conceptID="Mot1" novelty="None" advantage="None"/><text>The development of multifunctional, high throughput lab-on-a-chip devices depends heavily on the ability to measure flow rate and perform quantitative analysis of fluids in minute volumes.</text></s> <s sid="9"><CoreSc1 atype="GSC" type="Met" conceptID="Met2" novelty="Old" advantage="None"/><text>Traditionally, there have been many MEMS-based (MEMS = microelectromechanical system) flow sensors for gaseous flows.<REF TYPE="P" ID="cit1">1</REF></text></s> <s sid="10"><CoreSc1 atype="GSC" type="Bac" conceptID="Bac1" novelty="None" advantage="None"/><text>In recent times, there has been some advancement in measuring micro-flows of liquids.</text></s> <s sid="11"><CoreSc1 atype="GSC" type="Met" conceptID="Met3" novelty="Old" advantage="None"/><text>Examples of sensing principles explored in the measurement of microfluidic flow are heat transfer detection,<REF TYPE="P" ID="cit2 cit3 cit4">2–4</REF> molecular sensing,<REF TYPE="P" ID="cit5">5</REF> atomic emission detection,<REF TYPE="P" ID="cit6">6</REF> streaming potential measurements,<REF TYPE="P" ID="cit7">7</REF> electrical impedance tomography,<REF TYPE="P" ID="cit8">8</REF> ion-selective field-effect transitors<REF TYPE="P" ID="cit9">9</REF> and periodic flapping motion detection.<REF TYPE="P" ID="cit10">10</REF></text></s> <s sid="12"><CoreSc1 atype="GSC" type="Bac" conceptID="Bac2" novelty="None" advantage="None"/><text>Flow sensors form the integral part of micrototal analysis systems<REF TYPE="P" ID="cit11">11</REF> with multisensors.</text></s> <s sid="13"><CoreSc1 atype="GSC" type="Met" conceptID="Met4" novelty="Old" advantage="None"/><text>Conversely, a measure of electric current is used for pumping a measurable flow rate of fluids in electro-osmotic flow (EOF).<REF TYPE="P" ID="cit12">12</REF></text></s></P><P><s sid="14"><CoreSc1 atype="GSC" type="Met" conceptID="Met5" novelty="Old" advantage="None"/><text>Flow sensors based on sensing the temperature difference between two points in the microchannel<REF TYPE="P" ID="cit2 cit3 cit4">2–4</REF> can sense very low flows.</text></s> <s sid="15"><CoreSc1 atype="GSC" type="Met" conceptID="Met5" novelty="Old" advantage="No"/><text>However, such flow sensors require a complicated design and the integration of the heater, temperature sensors and membrane shielding is difficult to implement.</text></s> <s sid="16"><CoreSc1 atype="GSC" type="Met" conceptID="Met5" novelty="Old" advantage="No"/><text>Moreover, the sensitivity and accuracy of the flow sensors depend on the environment associated in the heat transfer.</text></s> <s sid="17"><CoreSc1 atype="GSC" type="Met" conceptID="Met3" novelty="Old" advantage="No"/><text>Most other methods are not capable of measuring very low flow rates.</text></s> <s sid="18"><CoreSc1 atype="GSC" type="Met" conceptID="Met1" novelty="New" advantage="None"/><text>We consider flow sensing by directly measuring the electrical admittance of the fluid using two surface electrodes.</text></s></P><P><s sid="19"><CoreSc1 atype="GSC" type="Bac" conceptID="Bac3" novelty="None" advantage="None"/><text>In electrolytes flowing in a microchannel under laminar flow conditions, a parabolic velocity profile exists and so the ions in the middle of the channels travel faster than those near the walls.</text></s> <s sid="20"><CoreSc1 atype="GSC" type="Mod" conceptID="Mod1" novelty="None" advantage="None"/><text>This results in the redistribution of ions within the electric double layer (EDL) formed in the channel.<REF TYPE="P" ID="cit13">13</REF></text></s> <s sid="21"><CoreSc1 atype="GSC" type="Mod" conceptID="Mod1" novelty="None" advantage="None"/><text>The ac voltage across the channel electrodes (Fig. 3) drives the ions back and forth across the electrodes.</text></s> <s sid="22"><CoreSc1 atype="GSC" type="Mod" conceptID="Mod1" novelty="None" advantage="None"/><text>The ionic redistribution develops electrokinetic effects and contributes to change in electric admittance.</text></s> <s sid="23"><CoreSc1 atype="GSC" type="Met" conceptID="Met1" novelty="New" advantage="Yes"/><text>Thus the flow of fluid is very sensitive to the admittance across microelectrodes<REF TYPE="P" ID="cit14 cit15">14,15</REF> in the flow channels, and measuring the increase in admittance precisely accounts for the flow rate.</text></s> <s sid="24"><CoreSc1 atype="GSC" type="Met" conceptID="Met1" novelty="New" advantage="Yes"/><text>Our flow sensor operating with optimized electric parameters can be efficient and accurate for precise values of flows.</text></s> <s sid="25"><CoreSc1 atype="GSC" type="Met" conceptID="Met1" novelty="New" advantage="Yes"/><text>This method is relatively simple and suitable for most of the chemical and biochemical microfluidic applications since most of the reagents used are electrolytes.</text></s> <s sid="26"><CoreSc1 atype="GSC" type="Obj" conceptID="Obj1" novelty="New" advantage="None"/><text>In this paper, we present such a flow sensor based on the measurement of electrical admittance.</text></s></P><DIV DEPTH="2"><HEADER>Principle</HEADER><P><s sid="27"><CoreSc1 atype="GSC" type="Mod" conceptID="Mod2" novelty="None" advantage="None"/><text>In hydrodynamic conditions, forced convection dominates the transport of ions to the electrodes within the flow channels.</text></s> <s sid="28"><CoreSc1 atype="GSC" type="Mod" conceptID="Mod2" novelty="None" advantage="None"/><text>When the width of the microfluidic channel is very small compared to the length of the channel, the lateral diffusion of the ions is significant under laminar flow.</text></s> <s sid="29"><CoreSc1 atype="GSC" type="Mod" conceptID="Mod3" novelty="None" advantage="None"/><text>Under an ac electrical signal applied across the channel, the equivalent circuit<REF TYPE="P" ID="cit16">16</REF> of the microsystem is shown in Fig. 1.</text></s> <s sid="30"><CoreSc1 atype="GSC" type="Mod" conceptID="Mod3" novelty="None" advantage="None"/><text>The electrical double layer<REF TYPE="P" ID="cit17">17</REF> formed across the channel is formed from two capacitances namely diffuse layer capacitance (<IT>C</IT><SB>s</SB>) and the outer Helmholtz plane capacitance (<IT>C</IT><SB>e</SB>).</text></s> <s sid="31"><CoreSc1 atype="GSC" type="Mod" conceptID="Mod3" novelty="None" advantage="None"/><text>The former is due to ion excess or depletion in the channel, and the latter is due to the free electrons at the electrodes and is independent of the electrolyte concentration.</text></s> <s sid="32"><CoreSc1 atype="GSC" type="Mod" conceptID="Mod3" novelty="None" advantage="None"/><text>The smaller of these capacitances dominates the admittance since these two capacitances are in series.</text></s> <s sid="33"><CoreSc1 atype="GSC" type="Goa" conceptID="Goa1" novelty="None" advantage="None"/><text>The frequency of the applied ac voltage, flow rate and conductivity of the fluid are the factors affecting the admittance of the fluidic system and our flow sensing principle is based on the optimization of these parameters.</text></s></P><P><s sid="34"><CoreSc1 atype="GSC" type="Mod" conceptID="Mod4" novelty="None" advantage="None"/><text>For an electrochemical oxidation of a species A to A<SP>+</SP> in a microchannel, the convective–diffusive equation for mass transport under steady state conditions is given by eqn. (1):where [A] is the concentration of the species, <IT>D</IT><SB>A</SB> is the diffusion coefficient and <IT>v<SB>x</SB></IT> is the velocity in the direction of flow.</text></s> <s sid="35"><CoreSc1 atype="GSC" type="Mod" conceptID="Mod4" novelty="None" advantage="None"/><text>The first term is the lateral diffusion in the microchannel and the second term is the transport along the length of the channel.</text></s> <s sid="36"><CoreSc1 atype="GSC" type="Mod" conceptID="Mod4" novelty="None" advantage="None"/><text>Under steady state flow conditions the boundary condition is given by eqn. (2).</text></s> <s sid="37"><CoreSc1 atype="GSC" type="Mod" conceptID="Mod5" novelty="None" advantage="None"/><text>The solution of this equation predicts the mass transport limited current (<IT>i</IT><SB>L</SB>)<REF TYPE="P" ID="cit18">18</REF> as a function of flow rate, <IT>Q</IT> as given by eqn. (3):where <IT>n</IT> is the number of electrons transferred, <IT>F</IT>, the Faraday constant, <IT>x</IT><SB>e</SB> is the electrode length, <IT>h</IT>, the cell half-height, <IT>d</IT>, the width of the cell and <IT>w</IT>, the electrode width.</text></s> <s sid="38"><CoreSc1 atype="GSC" type="Mod" conceptID="Mod5" novelty="None" advantage="None"/><text>It is to be noted that the current due to flow of electrolyte is directly proportional to the cube root of volume flow rate of the fluid.</text></s> <s sid="39"><CoreSc1 atype="GSC" type="Mod" conceptID="Mod5" novelty="None" advantage="None"/><text>The ac voltage signal is considered rather than dc voltage since the application of an ac voltage in the flow sensor does not promote any electrode reaction.</text></s> <s sid="40"><CoreSc1 atype="GSC" type="Mod" conceptID="Mod5" novelty="None" advantage="None"/><text>Optimization of the electrical parameters like voltage and frequency of the ac signal are considered as an operating condition for measuring low flow rates.</text></s> <s sid="41"><CoreSc1 atype="GSC" type="Mod" conceptID="Mod5" novelty="None" advantage="None"/><text>This optimizes the distance of movement of ions and their relaxation behavior across the channel electrodes so that the current admittance suffered is maximum.</text></s></P></DIV></DIV><DIV DEPTH="1"><HEADER>Experiment</HEADER><DIV DEPTH="2"><HEADER>Fabrication</HEADER><P><s sid="42"><CoreSc1 atype="GSC" type="Exp" conceptID="Exp1" novelty="None" advantage="None"/><text>The flow sensor is fabricated<REF TYPE="P" ID="cit19">19</REF> on a glass substrate with gold surface electrodes (Fig. 2a) and the microfluidic channel is made on PDMS.</text></s> <s sid="43"><CoreSc1 atype="GSC" type="Exp" conceptID="Exp1" novelty="None" advantage="None"/><text>Gold metal of thickness 100 nm is deposited on an adhesion layer of titanium with thickness 20 nm using e-beam deposition.</text></s> <s sid="44"><CoreSc1 atype="GSC" type="Exp" conceptID="Exp1" novelty="None" advantage="None"/><text>A spinned layer of Shipley photoresist (1827) is used for patterning (Fig. 2b) the metal.</text></s> <s sid="45"><CoreSc1 atype="GSC" type="Exp" conceptID="Exp1" novelty="None" advantage="None"/><text>The electrodes are patterned by etching gold and titanium with potassium iodide solution (KI + I<SB>2</SB> + H<SB>2</SB>O = 4:1:40) and 2% HF respectively.</text></s> <s sid="46"><CoreSc1 atype="GSC" type="Exp" conceptID="Exp1" novelty="None" advantage="None"/><text>The Shipley photoresist is removed with acetone.</text></s> <s sid="47"><CoreSc1 atype="GSC" type="Exp" conceptID="Exp1" novelty="None" advantage="None"/><text>The distance between the electrodes is 100 µm and the length of the electrodes is 5 mm.</text></s> <s sid="48"><CoreSc1 atype="GSC" type="Exp" conceptID="Exp1" novelty="None" advantage="None"/><text>Gold electrical lines are patterned on the glass as shown in Fig. 2a for the electrical measurement.</text></s> <s sid="49"><CoreSc1 atype="GSC" type="Exp" conceptID="Exp1" novelty="None" advantage="None"/><text>Measurement is performed across one of the three electrodes.</text></s> <s sid="50"><CoreSc1 atype="GSC" type="Exp" conceptID="Exp1" novelty="None" advantage="None"/><text>PDMS channels of width 500 µm are made from an SU8 mold.<REF TYPE="P" ID="cit20">20</REF></text></s> <s sid="51"><CoreSc1 atype="GSC" type="Exp" conceptID="Exp1" novelty="None" advantage="None"/><text>Glass and PDMS are bonded together after treatment with oxygen plasma for 1 min.</text></s> <s sid="52"><CoreSc1 atype="GSC" type="Exp" conceptID="Exp1" novelty="None" advantage="None"/><text>The fluidic channel is aligned with the parallel electrodes using a stereo microscope.</text></s></P></DIV><DIV DEPTH="2"><HEADER>Measurements</HEADER><P><s sid="53"><CoreSc1 atype="GSC" type="Exp" conceptID="Exp2" novelty="None" advantage="None"/><text>The measuring instrumentation is similar to that used in strain gauge or thermocouple interfaces.</text></s> <s sid="54"><CoreSc1 atype="GSC" type="Exp" conceptID="Exp2" novelty="None" advantage="None"/><text>An ac voltage is applied across the channel electrodes in series with a standard resistor.</text></s> <s sid="55"><CoreSc1 atype="GSC" type="Exp" conceptID="Exp2" novelty="None" advantage="None"/><text>The voltage across the resistor is fed to a National Instrument's data acquisition card (NI DAQ PCI 6024E) through the signal conditioner (SCXI 1100) as shown in Fig. 3.</text></s> <s sid="56"><CoreSc1 atype="GSC" type="Exp" conceptID="Exp2" novelty="None" advantage="None"/><text>The rms values of voltage across the standard resistor are measured in Labview with a scanning rate of 20 000 samples per s and averaging every 10 000 samples.</text></s></P><P><s sid="57"><CoreSc1 atype="GSC" type="Exp" conceptID="Exp2" novelty="None" advantage="None"/><text>Sodium hydroxide (NaOH) solutions with conductivities ranging from 5 to 200 mS cm<SP>–1</SP> (corresponding to 0.01 M to 1 M) are prepared with NaOH pellets bought from Fisher Scientific.</text></s> <s sid="58"><CoreSc1 atype="GSC" type="Exp" conceptID="Exp2" novelty="None" advantage="None"/><text>The concentration of the NaOH solution is chosen at 0.8 M and experiments are carried out for frequency and current response.</text></s> <s sid="59"><CoreSc1 atype="GSC" type="Exp" conceptID="Exp2" novelty="None" advantage="None"/><text>Microfluidic flow is maintained at a constant flow rate using a Harvard Picoplus Syringe pump.</text></s> <s sid="60"><CoreSc1 atype="GSC" type="Exp" conceptID="Exp2" novelty="None" advantage="None"/><text>An ac signal of rms voltage 0.05 V is applied in the circuit by a signal generator.</text></s> <s sid="61"><CoreSc1 atype="GSC" type="Exp" conceptID="Exp2" novelty="None" advantage="None"/><text>The rms voltage across the parallel microelectrodes increases to 0.04 V after wetting the channel (with no flow of electrolyte through it).</text></s> <s sid="62"><CoreSc1 atype="GSC" type="Obs" conceptID="Obs1" novelty="None" advantage="None"/><text>With some trials of experiments it was found that the current values grow and decay exponentially and stay constant after 1 min.</text></s> <s sid="63"><CoreSc1 atype="GSC" type="Exp" conceptID="Exp2" novelty="None" advantage="None"/><text>In order to keep the uniformity in all the experiments, the fluid is allowed to flow in the channel for 1 min and the flow is switched off for 1 min before any other measurement.</text></s> <s sid="64"><CoreSc1 atype="GSC" type="Exp" conceptID="Exp2" novelty="None" advantage="None"/><text>The current flowing across the pair of electrodes is calculated from the measured voltage across the standard resistor of 1 kΩ.</text></s> <s sid="65"><CoreSc1 atype="GSC" type="Obs" conceptID="Obs1" novelty="None" advantage="None"/><text>The current exponentially grows when the flow is switched on and then stays constant.</text></s> <s sid="66"><CoreSc1 atype="GSC" type="Obs" conceptID="Obs1" novelty="None" advantage="None"/><text>After switching off the flow, the current again decays exponentially until it reaches a constant value.</text></s> <s sid="67"><CoreSc1 atype="GSC" type="Exp" conceptID="Exp2" novelty="None" advantage="None"/><text>The difference between two constant values of current gives the current increase due to flow and is measured in all the experiments.</text></s></P></DIV></DIV><DIV DEPTH="1"><HEADER>Results and discussion</HEADER><P><s sid="68"><CoreSc1 atype="GSC" type="Obs" conceptID="Obs2" novelty="None" advantage="None"/><text>Flow of fluid is quantitatively analyzed for the flow sensor characteristics in steps of 5 µL min<SP>–1</SP>, and an almost linear response was shown (as in Fig. 4) for the currents measured with flow rates.</text></s> <s sid="69"><CoreSc1 atype="GSC" type="Mod" conceptID="Mod5" novelty="None" advantage="None"/><text>The ac frequency used in this case is 500 Hz at 0.05 V. As pointed out earlier, the current increase, which is a measure of admittance is proportional to the cube root of volume flow rate.</text></s> <s sid="70"><CoreSc1 atype="GSC" type="Met" conceptID="Met6" novelty="New" advantage="None"/><text>NaOH is used in this paper as a convenient test solution to demonstrate the flow sensor.</text></s> <s sid="71"><CoreSc1 atype="GSC" type="Met" conceptID="Met6" novelty="New" advantage="No"/><text>The problem with higher concentration NaOH is that it tends to absorb the atmospheric CO<SB>2</SB> and form carbonic acid.</text></s> <s sid="72"><CoreSc1 atype="GSC" type="Res" conceptID="Res1" novelty="None" advantage="None"/><text>This is reflected in the drift of the baseline in Fig 4a.</text></s> <s sid="73"><CoreSc1 atype="GSC" type="Met" conceptID="Met6" novelty="New" advantage="Yes"/><text>The drift in the baseline can be calibrated with respect to time.</text></s> <s sid="74"><CoreSc1 atype="GSC" type="Obs" conceptID="Obs3" novelty="None" advantage="None"/><text>However this drift in baseline is not seen for biochemical solutions that are buffered.</text></s></P><P><s sid="75"><CoreSc1 atype="GSC" type="Exp" conceptID="Exp3" novelty="None" advantage="None"/><text>In another experiment, the frequency of the ac signal is swept from 10 Hz to 5 kHz in steps of 10 Hz in the 10–100 Hz range, 100 Hz in the 100–1000 range and 1 kHz in the 1–5 kHz range.</text></s> <s sid="76"><CoreSc1 atype="GSC" type="Res" conceptID="Res2" novelty="None" advantage="None"/><text>Since the equivalent circuit of the microchannel is capacitive dominant, the base current (with no flow) increases with frequency.</text></s> <s sid="77"><CoreSc1 atype="GSC" type="Exp" conceptID="Exp3" novelty="None" advantage="None"/><text>At each frequency, the measurement of current before and after flow is brought to a constant value by waiting for 1 min.</text></s> <s sid="78"><CoreSc1 atype="GSC" type="Obs" conceptID="Obs4" novelty="None" advantage="None"/><text>The redistribution of ions in the channel causes an increase or decrease of current.</text></s> <s sid="79"><CoreSc1 atype="GSC" type="Obs" conceptID="Obs4" novelty="None" advantage="None"/><text>It is observed that the admittance is maximized at 500 Hz as shown in Fig. 5.</text></s> <s sid="80"><CoreSc1 atype="GSC" type="Res" conceptID="Res3" novelty="None" advantage="None"/><text>This is due to the competitive capacitive effects of the <IT>C</IT>e and <IT>C</IT>s as described earlier.</text></s> <s sid="81"><CoreSc1 atype="GSC" type="Res" conceptID="Res4" novelty="None" advantage="None"/><text>It is to be understood that the efficiency of the flow sensor is found to be high at this frequency.</text></s></P><P><s sid="82"><CoreSc1 atype="GSC" type="Res" conceptID="Res4" novelty="None" advantage="None"/><text>The ac voltage applied has a great influence on the flow driven current.</text></s> <s sid="83"><CoreSc1 atype="GSC" type="Res" conceptID="Res5" novelty="None" advantage="None"/><text>Higher voltage increases the diffusive region in the channel which in turn decreases the diffusive capacitance (<IT>C</IT>s).</text></s> <s sid="84"><CoreSc1 atype="GSC" type="Res" conceptID="Res5" novelty="None" advantage="None"/><text>But the contribution of the capacitance at outer Helmholtz plane becomes more prominent and the admittance increases.</text></s> <s sid="85"><CoreSc1 atype="GSC" type="Res" conceptID="Res6" novelty="None" advantage="None"/><text>Furthermore, at voltages more than 400 mV, partial electrolysis takes place and the effective current decreases with voltage.</text></s> <s sid="86"><CoreSc1 atype="GSC" type="Obs" conceptID="Obs5" novelty="None" advantage="None"/><text>Fig. 6 shows the optimization of voltage of the ac signal used in the flow sensor.</text></s> <s sid="87"><CoreSc1 atype="GSC" type="Obs" conceptID="Obs5" novelty="None" advantage="None"/><text>The V–I characteristic of the flow sensor (with no flow) shows a parabolic response similar to the conductivity measurement of electrolytes.</text></s> <s sid="88"><CoreSc1 atype="GSC" type="Exp" conceptID="Exp4" novelty="None" advantage="None"/><text>Thus the flow sensor is tuned for the ac voltage of 400 mV.</text></s></P><P><s sid="89"><CoreSc1 atype="GSC" type="Exp" conceptID="Exp4" novelty="None" advantage="None"/><text>NaOH solution of different concentrations were studied in the flow sensor.</text></s> <s sid="90"><CoreSc1 atype="GSC" type="Obs" conceptID="Obs6" novelty="None" advantage="None"/><text>It is found that there is an optimum value of the concentration of the electrolyte for the flow sensor to be at its maximum efficiency.</text></s> <s sid="91"><CoreSc1 atype="GSC" type="Obs" conceptID="Obs6" novelty="None" advantage="None"/><text>Fig. 7 shows that the concentration of the flow sensor is optimized at 0.2 M. At lower concentrations the admittance increases with more numbers of ions in the fluid system.</text></s> <s sid="92"><CoreSc1 atype="GSC" type="Res" conceptID="Res7" novelty="None" advantage="None"/><text>When the ionic concentration is too large the flow of fluid does not further increase the admittance because of inter-ionic interactions.</text></s> <s sid="93"><CoreSc1 atype="GSC" type="Res" conceptID="Res7" novelty="None" advantage="None"/><text>However generally the buffers or electrolytes used in microfluidic application are in mM concentration and the optimization of concentration is not necessary.</text></s></P><P><s sid="94"><CoreSc1 atype="GSC" type="Exp" conceptID="Exp5" novelty="None" advantage="None"/><text>Using the optimized electrical parameters (<IT>f</IT> = 500 Hz, <IT>V</IT> = 0.4 V and concentration = 0.2 M), the flow sensor is designed for measuring very low values of flow rate starting at 0.05 µL min<SP>–1</SP> (&lt;1 nL s<SP>–1</SP>).</text></s> <s sid="95"><CoreSc1 atype="GSC" type="Res" conceptID="Res8" novelty="None" advantage="None"/><text>The response shows a cube root behavior even at very low flow rates as shown in Fig. 8.</text></s> <s sid="96"><CoreSc1 atype="GSC" type="Obs" conceptID="Obs7" novelty="None" advantage="None"/><text>The sensitivity at these optimizations is 5.2 × 10<SP>–4</SP> mA/(µL/min).</text></s> <s sid="97"><CoreSc1 atype="GSC" type="Exp" conceptID="Exp6" novelty="None" advantage="None"/><text>In another experiment, fluorescent beads of diameter 2.5 µm are mixed with NaOH and sent through the channel.</text></s> <s sid="98"><CoreSc1 atype="GSC" type="Exp" conceptID="Exp6" novelty="None" advantage="None"/><text>The motion of the beads at the flow rates .05, 0.1, 0.2, 0.4, and 0.6 µL min<SP>–1</SP> are recorded using optical video microscopy at 30, 60, 120, 250, 250 frames per s respectively, and the beads at a particular stream are analyzed and averaged to predict the velocity response at very low flow rates.</text></s> <s sid="99"><CoreSc1 atype="GSC" type="Res" conceptID="Res9" novelty="None" advantage="None"/><text>The sensor results are compared with the velocity of beads (the symbol * in Fig. 8) and shows similar response.</text></s> <s sid="100"><CoreSc1 atype="GSC" type="Res" conceptID="Res9" novelty="None" advantage="None"/><text>Thus the calibration of the flow sensor is accomplished using the velocity measurements with beads.</text></s></P><P><s sid="101"><CoreSc1 atype="GSC" type="Exp" conceptID="Exp7" novelty="None" advantage="None"/><text>Though this paper presents NaOH as the fluid used for demonstration of this flow sensor, different electrolytes and biochemical buffers have been tested for the sensitivity.</text></s> <s sid="102"><CoreSc1 atype="GSC" type="Exp" conceptID="Exp7" novelty="None" advantage="None"/><text>CaCl<SB>2</SB>, KCl and KOH (from Fisher Scientific) and a concentration of 0.8 M is used.</text></s> <s sid="103"><CoreSc1 atype="GSC" type="Exp" conceptID="Exp7" novelty="None" advantage="None"/><text>Dulbecco's Phosphate Buffered Saline (D-PBS) solution and Modified Eagle Medium (D-MEM) (high glucose) buffer are bought from GIBCO and are used in the same concentration.</text></s> <s sid="104"><CoreSc1 atype="GSC" type="Exp" conceptID="Exp7" novelty="None" advantage="None"/><text>Optimization of frequency of the ac signal alone is done for the fluids at 50 mV rms applied voltage.</text></s> <s sid="105"><CoreSc1 atype="GSC" type="Exp" conceptID="Exp7" novelty="None" advantage="None"/><text>The typical increase of currents is measured for the flow rate of 10 µL min<SP>–1</SP> and the sensitivity values are tabulated in Table 1.</text></s> <s sid="106"><CoreSc1 atype="GSC" type="Bac" conceptID="Bac4" novelty="None" advantage="None"/><text>These buffers and reagents are used in chemical and biochemical experiments.</text></s> <s sid="107"><CoreSc1 atype="GSC" type="Met" conceptID="Met1" novelty="New" advantage="Yes"/><text>When these fluids are used in lab-on-chips, the flow rates of the fluids can be determined using the flow sensor we described in this paper.</text></s> <s sid="108"><CoreSc1 atype="GSC" type="Met" conceptID="Met1" novelty="New" advantage="Yes"/><text>It is to be noted that though we optimized the conductivity of the electrolyte for this study, it is not required and therefore the sensor can be used with arbitrary concentrations.</text></s> <s sid="109"><CoreSc1 atype="GSC" type="Met" conceptID="Met1" novelty="New" advantage="No"/><text>Conductivity depends on the constituent materials and changing the conductivity of certain buffers/reagents will alter the biochemical reaction.</text></s></P><P><s sid="110"><CoreSc1 atype="GSC" type="Met" conceptID="Met1" novelty="New" advantage="Yes"/><text>The principle of measuring electrical admittance laid out in this paper can be used to decipher parameters other than flow.</text></s> <s sid="111"><CoreSc1 atype="GSC" type="Met" conceptID="Met7" novelty="Old" advantage="None"/><text>There have been several reports<REF TYPE="P" ID="cit21 cit22">21,22</REF> on the detection of biomelecules and cells in lab-on-chip devices based on impedance spectroscopy of the solution.</text></s> <s sid="112"><CoreSc1 atype="GSC" type="Met" conceptID="Met7" novelty="Old" advantage="No"/><text>In these methods, the measurements are done with static fluids.</text></s> <s sid="113"><CoreSc1 atype="GSC" type="Met" conceptID="Met1" novelty="New" advantage="Yes"/><text>By measuring impedance change due to different conditions of flow it is possible to investigate the constituents of the solution.</text></s> <s sid="114"><CoreSc1 atype="GSC" type="Con" conceptID="Con1" novelty="None" advantage="None"/><text>In the future, impedance spectroscopy based on differential flow can thus be used to characterize electrolytes including biomolecules, cells or microbes under laminar flow.</text></s></P></DIV><DIV DEPTH="1"><HEADER>Conclusions</HEADER><P><s sid="115"><CoreSc1 atype="GSC" type="Obj" conceptID="Obj1" novelty="New" advantage="None"/><text>A novel microfluidic flow sensor based on electrical admittance measurement is designed, fabricated and characterized.</text></s> <s sid="116"><CoreSc1 atype="GSC" type="Res" conceptID="Res10" novelty="None" advantage="None"/><text>The efficiency of the flow sensor is maximized by the optimization of electrical parameters such as frequency and voltage of the applied ac signal.</text></s> <s sid="117"><CoreSc1 atype="GSC" type="Exp" conceptID="Exp5" novelty="None" advantage="None"/><text>These optimized values are then used to measure flow rates as low as 1 nL s<SP>–1</SP>.</text></s> <s sid="118"><CoreSc1 atype="GSC" type="Exp" conceptID="Exp6" novelty="None" advantage="None"/><text>The response of the flow sensor is compared with the velocity of microbeads in the same channel using video microscopy and image processing.</text></s> <s sid="119"><CoreSc1 atype="GSC" type="Met" conceptID="Met1" novelty="New" advantage="Yes"/><text>Some of the advantages of the flow sensor include simplicity in design, integration to most microfluidic platforms, high signal-to-noise ratio, measurements of a wide range of liquids including biochemical buffers and compatibility with micromachining processes.</text></s> <s sid="120"><CoreSc1 atype="GSC" type="Con" conceptID="Con1" novelty="None" advantage="None"/><text>This flow sensor has the potential to measure a broad range of liquid properties, including the characterization of biomolecules and microbes in microfluidic channels.</text></s></P></DIV></BODY></PAPER>